Metadata-Version: 2.1
Name: my-library-vnstock
Version: 0.1.0
Summary: A library with secret functions
Home-page: https://github.com/your_username/my_library
Author: Your Name
Author-email: your.email@example.com
Classifier: Programming Language :: Python :: 3
Classifier: License :: OSI Approved :: MIT License
Classifier: Operating System :: OS Independent
Requires-Python: >=3.6
